{
   "data": [
      {
         "exercise": 1,
         "part": 1,
         "has_answer": false,
         "answer": "",
         "id": 201447618559423401
      },
      {
         "exercise": 1,
         "part": 2,
         "has_answer": false,
         "answer": "",
         "id": 399497697450985119
      },
      {
         "exercise": 1,
         "part": 3,
         "has_answer": true,
         "answer": [
            10,
            11,
            8,
            7,
            1,
            5,
            9
         ],
         "id": 845666446746636561
      },
      {
         "exercise": 1,
         "part": 4,
         "has_answer": true,
         "answer": [
            "minikube start*",
            "minikube stop"
         ],
         "id": 143486463589351288
      },
      {
         "exercise": 2,
         "part": 1,
         "has_answer": false,
         "answer": "",
         "id": 890560088784296499
      },
      {
         "exercise": 2,
         "part": 2,
         "has_answer": false,
         "answer": "",
         "id": 194596570045836192
      },
      {
         "exercise": 2,
         "part": 3,
         "has_answer": true,
         "answer": [
            [
               "kubectl delete service palve",
               "kubectl delete svc palve"
            ],
            [
               "kubectl get replicationcontrollers",
               "kubectl get rc"
            ],
            [
               "kubectl edit role/johtaja"
            ],
            [
               "kubectl scale --replicas=3 deployment/käyttö",
               "kubectl scale --replicas=3 deploy/käyttö"
            ],
            [
               "kubectl expose pod validi-säiliö"
            ],
            [
               "kubectl describe jobs"
            ]
         ],
         "id": 303367561700993572
      },
      {
         "exercise": 2,
         "part": 4,
         "has_answer": true,
         "answer": [
            "kubectl create deployment !insert --image=gcr.io/google-samples/kubernetes-bootcamp:v1",
            "kubectl get deployments"
         ],
         "id": 479321856943395484
      }
   ]
}