{
    "data": [
        {
            "code": 1,
            "return": "Ongelmatilanne komentorivikäyttöliittymässä", 
            "details": "Komentoa ajettaessa tapahtui ongelma."
        },
        {
            "code": 2,
            "return": "Väärä komento", 
            "details": "Käyttämäsi komento on väärä."
        },
        {
            "code": 3,
            "return": "Väärä komento", 
            "details": "Käyttämäsi alakomento on väärä."
        },
        {
            "code": 0,
            "return": "Määrittelemätön ongelma", 
            "details": "Komennon ajaminen ei onnistunut."
        },
        {
            "code": 5,
            "return": "Komennon määrittelyssä ongelma", 
            "details": "Sinun tulee antaa vaadittava komento."
        },
        {
            "code": 6,
            "return": "Komennon ajamisessa ongelma", 
            "details": "Komentoa ei ole olemassa."
        }
    ]
 }