{
   "data": [
      {
         "username": "asd",
         "completed": [
            -1,
            -1
         ],
         "id": 332044124927160027
      },
      {
         "username": "a",
         "completed": [
            -1,
            -1
         ],
         "id": 121623826343705383
      },
      {
         "username": "s",
         "completed": [
            -1,
            -1
         ],
         "id": 126965664031374548
      },
      {
         "username": "w",
         "completed": [
            -1,
            -1
         ],
         "id": 303458795153261093
      },
      {
         "username": "q",
         "completed": [
            -1,
            -1
         ],
         "id": 164569289910159760
      },
      {
         "username": "g",
         "completed": [
            -1,
            -1
         ],
         "id": 163267649493651018
      }
   ]
}